setup.py
digHeightExtractor/__init__.py
digHeightExtractor/height_extractor.py
digHeightExtractor/height_helper.py
digHeightExtractor.egg-info/PKG-INFO
digHeightExtractor.egg-info/SOURCES.txt
digHeightExtractor.egg-info/dependency_links.txt
digHeightExtractor.egg-info/requires.txt
digHeightExtractor.egg-info/top_level.txt
test/__init__.py
test/test_groundtruth.py
test/test_height_extractor.py
test/test_height_helper.py
test/groundtruth/__init__.py