Metadata-Version: 1.1
Name: digHeightExtractor
Version: 0.1.0
Summary: digHeightExtractor
Home-page: https://github.com/usc-isi-i2/dig-height-extractor
Author: Amandeep Singh
Author-email: amandeep.s.saggu@gmail.com
License: UNKNOWN
Download-URL: https://github.com/usc-isi-i2/dig-height-extractor
Keywords: height,extractor
Platform: UNKNOWN
